{
  "gitSyncId": "66ddcee1c708760dabe974b0_48865ced-d848-41d3-84b9-63c5cccfc36a",
  "id": "Client Full_Service_JS.open_module",
  "pluginId": "js-plugin",
  "pluginType": "JS",
  "unpublishedAction": {
    "actionConfiguration": {
      "encodeParamsToggle": true,
      "jsArguments": [
        {
          "name": "butt"
        }
      ],
      "paginationType": "NONE",
      "timeoutInMillisecond": 10000
    },
    "collectionId": "Client Full_Service_JS",
    "confirmBeforeExecute": false,
    "datasource": {
      "isAutoGenerated": false,
      "name": "UNUSED_DATASOURCE",
      "pluginId": "js-plugin"
    },
    "dynamicBindingPathList": [
      {
        "key": "body"
      }
    ],
    "executeOnLoad": false,
    "fullyQualifiedName": "Service_JS.open_module",
    "name": "open_module",
    "pageId": "Client Full",
    "userSetOnLoad": false
  }
}