{
  "animateLoading": true,
  "borderRadius": "{{appsmith.theme.borderRadius.appBorderRadius}}",
  "bottomRow": 290,
  "boxShadow": "none",
  "canEscapeKeyClose": true,
  "canOutsideClickClose": true,
  "children": [
    {
      "bottomRow": 520,
      "canExtend": true,
      "detachFromLayout": true,
      "displayName": "Canvas",
      "dynamicBindingPathList": [],
      "flexLayers": [],
      "hideCard": true,
      "isDeprecated": false,
      "isDisabled": false,
      "isLoading": false,
      "isVisible": true,
      "key": "l1ckom2tha",
      "leftColumn": 0,
      "minHeight": 524,
      "minWidth": 450,
      "mobileBottomRow": 240,
      "mobileLeftColumn": 0,
      "mobileRightColumn": 365.5078125,
      "mobileTopRow": 0,
      "parentColumnSpace": 1,
      "parentId": "inf8lepkpn",
      "parentRowSpace": 1,
      "renderMode": "CANVAS",
      "responsiveBehavior": "fill",
      "rightColumn": 365.5078125,
      "shouldScrollContents": false,
      "topRow": 0,
      "type": "CANVAS_WIDGET",
      "version": 1,
      "widgetId": "y99lx14dir",
      "widgetName": "Canvas12"
    }
  ],
  "detachFromLayout": true,
  "displayName": "Modal",
  "dynamicBindingPathList": [
    {
      "key": "borderRadius"
    }
  ],
  "dynamicHeight": "FIXED",
  "dynamicTriggerPathList": [],
  "height": 524,
  "hideCard": false,
  "iconSVG": "/static/media/icon.d2ab7de0666eaef853cc2d330f86887b.svg",
  "isCanvas": true,
  "isDeprecated": false,
  "isLoading": false,
  "key": "fzmpvf05v3",
  "leftColumn": 1,
  "maxDynamicHeight": 9000,
  "minDynamicHeight": 24,
  "mobileBottomRow": 73,
  "mobileLeftColumn": 1,
  "mobileRightColumn": 25,
  "mobileTopRow": 49,
  "parentColumnSpace": 15.2294921875,
  "parentId": "0",
  "parentRowSpace": 10,
  "renderMode": "CANVAS",
  "rightColumn": 25,
  "searchTags": [
    "dialog",
    "popup",
    "notification"
  ],
  "shouldScrollContents": true,
  "topRow": 50,
  "type": "MODAL_WIDGET",
  "version": 2,
  "widgetId": "inf8lepkpn",
  "widgetName": "ct_edit_modal",
  "width": 1020.3
}