{
  "gitSyncId": "66ddcee1c708760dabe974b0_ff8553ae-300f-40d9-a723-79ba9ac56faa",
  "id": "Client Full_Client_address.districtName_ins",
  "pluginId": "js-plugin",
  "pluginType": "JS",
  "unpublishedAction": {
    "actionConfiguration": {
      "encodeParamsToggle": true,
      "jsArguments": [
        {
          "name": "state_name",
          "value": "{{client_state_ins.selectedOptionValue}}"
        },
        {
          "name": "jsonData",
          "value": "{{appsmith.store.client_pincodeDetails_ins}}"
        }
      ],
      "paginationType": "NONE",
      "timeoutInMillisecond": 10000
    },
    "collectionId": "Client Full_Client_address",
    "confirmBeforeExecute": false,
    "datasource": {
      "isAutoGenerated": false,
      "name": "UNUSED_DATASOURCE",
      "pluginId": "js-plugin"
    },
    "dynamicBindingPathList": [
      {
        "key": "body"
      }
    ],
    "executeOnLoad": false,
    "fullyQualifiedName": "Client_address.districtName_ins",
    "name": "districtName_ins",
    "pageId": "Client Full",
    "userSetOnLoad": false
  }
}