{
  "gitSyncId": "66ddcee1c708760dabe974b0_033e69d3-57c9-4b98-89a2-a23b54f116df",
  "id": "UserApproval_emp_pkg.fetch_int",
  "pluginId": "js-plugin",
  "pluginType": "JS",
  "unpublishedAction": {
    "actionConfiguration": {
      "encodeParamsToggle": true,
      "jsArguments": [
        {
          "name": "intid"
        }
      ],
      "paginationType": "NONE",
      "timeoutInMillisecond": 10000
    },
    "collectionId": "UserApproval_emp_pkg",
    "confirmBeforeExecute": false,
    "datasource": {
      "isAutoGenerated": false,
      "name": "UNUSED_DATASOURCE",
      "pluginId": "js-plugin"
    },
    "dynamicBindingPathList": [
      {
        "key": "body"
      }
    ],
    "executeOnLoad": false,
    "fullyQualifiedName": "emp_pkg.fetch_int",
    "name": "fetch_int",
    "pageId": "UserApproval",
    "userSetOnLoad": false
  }
}