{
  "gitSyncId": "66ddcee1c708760dabe974b0_239e17bf-4e5c-4315-ba8a-d6b8c850a844",
  "id": "Client Full_Client_Pkg.CallGetClint",
  "pluginId": "js-plugin",
  "pluginType": "JS",
  "unpublishedAction": {
    "actionConfiguration": {
      "encodeParamsToggle": true,
      "jsArguments": [],
      "paginationType": "NONE",
      "timeoutInMillisecond": 10000
    },
    "collectionId": "Client Full_Client_Pkg",
    "confirmBeforeExecute": false,
    "datasource": {
      "isAutoGenerated": false,
      "name": "UNUSED_DATASOURCE",
      "pluginId": "js-plugin"
    },
    "dynamicBindingPathList": [
      {
        "key": "body"
      }
    ],
    "executeOnLoad": false,
    "fullyQualifiedName": "Client_Pkg.CallGetClint",
    "name": "CallGetClint",
    "pageId": "Client Full",
    "userSetOnLoad": false
  }
}